README.md
setup.py
cwl_airflow_parser/__init__.py
cwl_airflow_parser/cwldag.py
cwl_airflow_parser/cwlstepoperator.py
cwl_airflow_parser/cwlutils.py
cwl_airflow_parser.egg-info/PKG-INFO
cwl_airflow_parser.egg-info/SOURCES.txt
cwl_airflow_parser.egg-info/dependency_links.txt
cwl_airflow_parser.egg-info/not-zip-safe
cwl_airflow_parser.egg-info/requires.txt
cwl_airflow_parser.egg-info/top_level.txt
cwl_airflow_parser/operators/__init__.py
cwl_airflow_parser/operators/cwljobdispatcher.py
cwl_airflow_parser/operators/cwljobgatherer.py
cwl_airflow_parser/utils/__init__.py
cwl_airflow_parser/utils/jwt_backend.py
cwl_airflow_parser/utils/server.py
cwl_airflow_parser/utils/trigger.py
cwl_airflow_parser/utils/cwls/__init__.py
cwl_airflow_parser/utils/dags/__init__.py
cwl_airflow_parser/utils/dags/clean_dag_run.py
cwl_airflow_parser/utils/dags/sleep_for_an_hour_cwl_docker.py